odoo/addons/partner_category_security/README.rst
odoo/addons/partner_category_security/__init__.py
odoo/addons/partner_category_security/__manifest__.py
odoo/addons/partner_category_security/i18n/es.po
odoo/addons/partner_category_security/i18n/partner_category_security.pot
odoo/addons/partner_category_security/models/__init__.py
odoo/addons/partner_category_security/models/res_partner.py
odoo/addons/partner_category_security/readme/CONTRIBUTORS.rst
odoo/addons/partner_category_security/readme/DESCRIPTION.rst
odoo/addons/partner_category_security/readme/USAGE.rst
odoo/addons/partner_category_security/security/ir.model.access.csv
odoo/addons/partner_category_security/security/security.xml
odoo/addons/partner_category_security/static/description/icon.png
odoo/addons/partner_category_security/static/description/index.html
odoo/addons/partner_category_security/tests/__init__.py
odoo/addons/partner_category_security/tests/test_partner_category_security.py
odoo/addons/partner_category_security/views/menu.xml
odoo14_addon_partner_category_security-14.0.1.0.1.dist-info/METADATA
odoo14_addon_partner_category_security-14.0.1.0.1.dist-info/WHEEL
odoo14_addon_partner_category_security-14.0.1.0.1.dist-info/top_level.txt
odoo14_addon_partner_category_security-14.0.1.0.1.dist-info/RECORD
